aihub/__aihub__.py
aihub/__algo__.py
aihub/__client__.py
aihub/__collection__.py
aihub/__file__.py
aihub/__helper__.py
aihub/__init__.py
aihub-0.0.9.9.dist-info/METADATA
aihub-0.0.9.9.dist-info/WHEEL
aihub-0.0.9.9.dist-info/top_level.txt
aihub-0.0.9.9.dist-info/zip-safe
aihub-0.0.9.9.dist-info/RECORD
